README.md
setup.py
hack12306/__init__.py
hack12306/auth.py
hack12306/base.py
hack12306/constants.py
hack12306/exceptions.py
hack12306/order.py
hack12306/pay.py
hack12306/query.py
hack12306/settings.py
hack12306/user.py
hack12306/utils.py
hack12306.egg-info/PKG-INFO
hack12306.egg-info/SOURCES.txt
hack12306.egg-info/dependency_links.txt
hack12306.egg-info/requires.txt
hack12306.egg-info/top_level.txt
tests/__init__.py
tests/config.py
tests/test_auth.py
tests/test_order.py
tests/test_pay.py
tests/test_query.py
tests/test_user.py