Metadata-Version: 1.1
Name: hack12306
Version: 0.1.13
Summary: 12306 Python SDK, packaging the 12306 API
Home-page: https://github.com/hack12306/hack12306
Author: Meng.yangyang
Author-email: mengyy_linux@163.com
License: MIT
Platform: UNKNOWN
Classifier: Programming Language :: Python :: 2
Classifier: License :: OSI Approved :: MIT License
Classifier: Operating System :: OS Independent
